scrape_youtube/__init__.py
scrape_youtube/scrapper.py
scrape_youtube-0.0.6.dist-info/METADATA
scrape_youtube-0.0.6.dist-info/WHEEL
scrape_youtube-0.0.6.dist-info/top_level.txt
scrape_youtube-0.0.6.dist-info/RECORD
